line_rich_menu/__init__.py
line_rich_menu/cli/__init__.py
line_rich_menu/cli/main.py
line_rich_menu/const.py
line_rich_menu/helper.py
line_rich_menu/menu.py
line_rich_menu-0.0.3.dist-info/entry_points.txt
line_rich_menu-0.0.3.dist-info/WHEEL
line_rich_menu-0.0.3.dist-info/METADATA
line_rich_menu-0.0.3.dist-info/RECORD
