Metadata-Version: 2.1
Name: line-rich-menu
Version: 0.0.3
Summary: Rich Menu CLI for Line Bot
Author: Nuttapat Koonarangsri
Author-email: webmaster@hackinteach.com
Requires-Python: >=3.7,<4.0
Classifier: Programming Language :: Python :: 3
Classifier: Programming Language :: Python :: 3.10
Classifier: Programming Language :: Python :: 3.7
Classifier: Programming Language :: Python :: 3.8
Classifier: Programming Language :: Python :: 3.9
Requires-Dist: click (>=8.1.3,<9.0.0)
Requires-Dist: line-bot-sdk (>=2.2.1,<3.0.0)
Requires-Dist: python-dotenv (>=0.20.0,<0.21.0)
Requires-Dist: python-magic (>=0.4.25,<0.5.0)
